yynb.py
yynb-0.3.1.dist-info/LICENSE
yynb-0.3.1.dist-info/WHEEL
yynb-0.3.1.dist-info/METADATA
yynb-0.3.1.dist-info/RECORD
