Metadata-Version: 2.1
Name: yynb
Version: 0.3.1
Summary: An amazing yynb package!
Home-page: https://github.com/yytql/YYNB
License: UNKNOWN
Author: YY
Author-email: 2907047490@qq.com
Classifier: License :: OSI Approved :: MIT License
